{
    "frame1_image": "frame_0030_crop.jpg",
    "frame2_image": "frame_0035_crop.jpg",
    "mask_area": [
        {
            "x": 372,
            "y": 313
        },
        {
            "x": 951,
            "y": 317
        },
        {
            "x": 990,
            "y": 756
        },
        {
            "x": 328,
            "y": 735
        }
    ],
    "source_points": [
        {
            "x": 458,
            "y": 640
        },
        {
            "x": 843,
            "y": 656
        }
    ],
    "target_points": [
        {
            "x": 584,
            "y": 637
        },
        {
            "x": 656,
            "y": 626
        }
    ]
}