{
    "frame1_image": "frame_0085_crop.jpg",
    "frame2_image": "frame_0078_crop.jpg",
    "mask_area": [
        {
            "x": 622,
            "y": 794
        },
        {
            "x": 275,
            "y": 788
        },
        {
            "x": 311,
            "y": 1021
        },
        {
            "x": 580,
            "y": 1022
        }
    ],
    "source_points": [
        {
            "x": 443,
            "y": 858
        },
        {
            "x": 440,
            "y": 888
        }
    ],
    "target_points": [
        {
            "x": 447,
            "y": 833
        },
        {
            "x": 450,
            "y": 947
        }
    ]
}